clang_tidy_checker/__init__.py
clang_tidy_checker/__main__.py
clang_tidy_checker/cache_model.py
clang_tidy_checker/cache_table.py
clang_tidy_checker/check_files.py
clang_tidy_checker/check_result.py
clang_tidy_checker/clang_tidy_executor.py
clang_tidy_checker/command_executor.py
clang_tidy_checker/config.py
clang_tidy_checker/main.py
clang_tidy_checker/search_checked_files.py
clang_tidy_checker/search_clang_tidy.py
clang_tidy_checker/source_hash_calculator.py
clang_tidy_checker-0.6.0.dist-info/METADATA
clang_tidy_checker-0.6.0.dist-info/WHEEL
clang_tidy_checker-0.6.0.dist-info/entry_points.txt
clang_tidy_checker-0.6.0.dist-info/RECORD
